redis_limiters/__init__.py
redis_limiters/base.py
redis_limiters/exceptions.py
redis_limiters/py.typed
redis_limiters/semaphore.lua
redis_limiters/semaphore.py
redis_limiters/test.py
redis_limiters/token_bucket.lua
redis_limiters/token_bucket.py
redis_limiters-0.7.0.dist-info/WHEEL
redis_limiters-0.7.0.dist-info/METADATA
redis_limiters-0.7.0.dist-info/RECORD
