Metadata-Version: 2.4
Name: redis-limiters
Version: 0.7.0
Summary: Python rate limiters backed by Redis
Keywords: redis,async,sync,rate,limiting,limiters
Author: Emil Aliyev, Sondre Lillebø Gundersen
Author-email: Emil Aliyev <ea01052002@gmail.com>, Sondre Lillebø Gundersen <sondrelg@live.no>
License-Expression: MIT
Classifier: Environment :: Web Environment
Classifier: Intended Audience :: Developers
Classifier: License :: OSI Approved :: MIT License
Classifier: Operating System :: OS Independent
Classifier: Programming Language :: Python
Classifier: Programming Language :: Python :: 3
Classifier: Programming Language :: Python :: 3.11
Classifier: Programming Language :: Python :: 3.12
Classifier: Programming Language :: Python :: 3.13
Classifier: Topic :: Internet :: WWW/HTTP
Classifier: Topic :: Internet :: WWW/HTTP :: Dynamic Content
Classifier: Topic :: Software Development
Classifier: Topic :: Software Development :: Libraries
Classifier: Topic :: Software Development :: Libraries :: Application Frameworks
Classifier: Topic :: Software Development :: Libraries :: Python Modules
Requires-Dist: pydantic
Requires-Dist: redis
Requires-Python: >=3.11
Project-URL: Homepage, https://github.com/Feuerstein-Org/redis-limiters
Project-URL: Repository, https://github.com/Feuerstein-Org/redis-limiters
